incredible_python/__init__.py
incredible_python/_base_client.py
incredible_python/_exceptions.py
incredible_python/client.py
incredible_python/helpers.py
incredible_python/transport.py
incredible_python/utils.py
incredible_python/resources/__init__.py
incredible_python/resources/agent.py
incredible_python/resources/answer.py
incredible_python/resources/completions.py
incredible_python/resources/conversation.py
incredible_python/resources/deep_research.py
incredible_python/resources/images.py
incredible_python/resources/integrations.py
incredible_python/resources/messages.py
incredible_python/resources/models.py
incredible_python/resources/ocr.py
incredible_python/resources/videos.py
incredible_python/resources/web_search.py
incredible_python/types/__init__.py
incredible_python/types/messages.py
incredible_python-1.0.0.dist-info/METADATA
incredible_python-1.0.0.dist-info/WHEEL
incredible_python-1.0.0.dist-info/top_level.txt
incredible_python-1.0.0.dist-info/RECORD
