Metadata-Version: 2.4
Name: incredible-python
Version: 1.0.0
Summary: Incredible API Python SDK compatible with Anthropics' client interface
Author-email: Incredible API Team <support@incredible.ai>
License: MIT
Project-URL: Homepage, https://github.com/Norditech-AB/incredible-python
Project-URL: Documentation, https://github.com/Norditech-AB/incredible-python
Project-URL: Source, https://github.com/Norditech-AB/incredible-python
Keywords: incredible,anthropic,sdk,client,ai
Classifier: Development Status :: 3 - Alpha
Classifier: Intended Audience :: Developers
Classifier: License :: OSI Approved :: MIT License
Classifier: Programming Language :: Python :: 3
Classifier: Programming Language :: Python :: 3.8
Classifier: Programming Language :: Python :: 3.9
Classifier: Programming Language :: Python :: 3.10
Classifier: Programming Language :: Python :: 3.11
Classifier: Programming Language :: Python :: 3.12
Classifier: Topic :: Software Development :: Libraries :: Python Modules
Requires-Python: >=3.8
Requires-Dist: httpx>=0.25
Requires-Dist: pydantic>=2.0
Requires-Dist: typing-extensions>=4.7
Requires-Dist: python-dotenv>=1.0.0
Provides-Extra: dev
Requires-Dist: pytest>=7.0; extra == "dev"
Requires-Dist: ruff>=0.5; extra == "dev"
